pytools_sshcli/__init__.py
pytools_sshcli/core.py
pytools_sshcli-0.1.1.dist-info/DESCRIPTION.rst
pytools_sshcli-0.1.1.dist-info/METADATA
pytools_sshcli-0.1.1.dist-info/RECORD
pytools_sshcli-0.1.1.dist-info/WHEEL
pytools_sshcli-0.1.1.dist-info/metadata.json
pytools_sshcli-0.1.1.dist-info/top_level.txt
